binaural/__init__.py
binaural/core.py
binaural-0.1.2.dist-info/LICENSE
binaural-0.1.2.dist-info/METADATA
binaural-0.1.2.dist-info/WHEEL
binaural-0.1.2.dist-info/top_level.txt
binaural-0.1.2.dist-info/RECORD
