Metadata-Version: 2.2
Name: binaural
Version: 0.1.2
Summary: A Python package for generating binaural beats and brainwave entrainment
Home-page: https://github.com/ishanoshada/binaural
Author: ishan Oshada
Author-email: ishan.kodithuwakku.offical@gmail.com
Keywords: binaural beats,brainwave entrainment,audio processing,sound synthesis
Classifier: Development Status :: 3 - Alpha
Classifier: Intended Audience :: Developers
Classifier: Intended Audience :: Science/Research
Classifier: License :: OSI Approved :: MIT License
Classifier: Operating System :: OS Independent
Classifier: Programming Language :: Python :: 3
Classifier: Programming Language :: Python :: 3.7
Classifier: Programming Language :: Python :: 3.8
Classifier: Programming Language :: Python :: 3.9
Classifier: Programming Language :: Python :: 3.10
Classifier: Topic :: Multimedia :: Sound/Audio
Classifier: Topic :: Scientific/Engineering :: Physics
License-File: LICENSE
Requires-Dist: numpy
Requires-Dist: scipy
Dynamic: author
Dynamic: author-email
Dynamic: classifier
Dynamic: description
Dynamic: description-content-type
Dynamic: home-page
Dynamic: keywords
Dynamic: requires-dist
Dynamic: summary
